rauc_hawkbit/__init__.py
rauc_hawkbit/config.cfg
rauc_hawkbit/dbus_client.py
rauc_hawkbit/rauc_dbus_ddi_client.py
rauc_hawkbit/ddi/__init__.py
rauc_hawkbit/ddi/cancel_action.py
rauc_hawkbit/ddi/client.py
rauc_hawkbit/ddi/deployment_base.py
rauc_hawkbit/ddi/softwaremodules.py
rauc_hawkbit-0.2.0.data/scripts/rauc-hawkbit-client
rauc_hawkbit-0.2.0.dist-info/COPYING
rauc_hawkbit-0.2.0.dist-info/METADATA
rauc_hawkbit-0.2.0.dist-info/WHEEL
rauc_hawkbit-0.2.0.dist-info/top_level.txt
rauc_hawkbit-0.2.0.dist-info/RECORD
