Metadata-Version: 2.1
Name: rauc-hawkbit
Version: 0.2.0
Summary: hawkBit client for RAUC
Home-page: https://github.com/rauc/rauc-hawkbit
Author: Bastian Stender and Enrico Joerns
Author-email: entwicklung@pengutronix.de
License: LGPL-2.1
Platform: UNKNOWN
Requires-Dist: aiohttp (>=3.3.2)
Requires-Dist: gbulb (>=0.5)
